LICENSE.txt
MANIFEST.in
README.md
setup.cfg
setup.py
gossipy/__init__.py
gossipy/gossipy.py
gossipy.egg-info/PKG-INFO
gossipy.egg-info/SOURCES.txt
gossipy.egg-info/dependency_links.txt
gossipy.egg-info/top_level.txt