Metadata-Version: 1.0
Name: gossipy
Version: 0.1
Summary: A basic chat class
Home-page: https://github.com/robertoreale/gossipy
Author: Roberto Reale
Author-email: rober.reale@gmail.com
License: UNKNOWN
Keywords: chat
Platform: UNKNOWN
